rest_framework_docs/__init__.py
rest_framework_docs/api_docs.py
rest_framework_docs/api_endpoint.py
rest_framework_docs/compat.py
rest_framework_docs/settings.py
rest_framework_docs/urls.py
rest_framework_docs/views.py
rest_framework_docs/static/rest_framework_docs/css/style.css
rest_framework_docs/static/rest_framework_docs/fonts/FontAwesome.otf
rest_framework_docs/static/rest_framework_docs/fonts/fontawesome-webfont.eot
rest_framework_docs/static/rest_framework_docs/fonts/fontawesome-webfont.svg
rest_framework_docs/static/rest_framework_docs/fonts/fontawesome-webfont.ttf
rest_framework_docs/static/rest_framework_docs/fonts/fontawesome-webfont.woff
rest_framework_docs/static/rest_framework_docs/fonts/fontawesome-webfont.woff2
rest_framework_docs/static/rest_framework_docs/fonts/glyphicons-halflings-regular.eot
rest_framework_docs/static/rest_framework_docs/fonts/glyphicons-halflings-regular.svg
rest_framework_docs/static/rest_framework_docs/fonts/glyphicons-halflings-regular.ttf
rest_framework_docs/static/rest_framework_docs/fonts/glyphicons-halflings-regular.woff
rest_framework_docs/static/rest_framework_docs/fonts/glyphicons-halflings-regular.woff2
rest_framework_docs/static/rest_framework_docs/js/dist.min.js
rest_framework_docs/static/rest_framework_docs/less/style.less
rest_framework_docs/templates/rest_framework_docs/base.html
rest_framework_docs/templates/rest_framework_docs/docs.html
rest_framework_docs/templates/rest_framework_docs/home.html
rest_framework_docs/templates/rest_framework_docs/components/fields_list.html
rest_framework_docs/templatetags/__init__.py
rest_framework_docs/templatetags/drfdocs_filters.py
tests/__init__.py
tests/models.py
tests/serializers.py
tests/settings.py
tests/tests.py
tests/urls.py
tests/views.py
drfdocs2-0.0.14.dist-info/LICENSE
drfdocs2-0.0.14.dist-info/METADATA
drfdocs2-0.0.14.dist-info/WHEEL
drfdocs2-0.0.14.dist-info/top_level.txt
drfdocs2-0.0.14.dist-info/RECORD
