Metadata-Version: 2.1
Name: drfdocs2
Version: 0.0.14
Summary: Documentation for Web APIs made with Django 2.0 & 3.0 and DRF
Home-page: http://www.drfdocs.com
Author: Emmanouil Konstantinidis
Author-email: manos@iamemmanouil.com
License: BSD
Platform: UNKNOWN
Classifier: Development Status :: 5 - Production/Stable
Classifier: Environment :: Web Environment
Classifier: Framework :: Django
Classifier: Intended Audience :: Developers
Classifier: License :: OSI Approved :: BSD License
Classifier: Operating System :: OS Independent
Classifier: Programming Language :: Python
Classifier: Programming Language :: Python :: 3.5
Classifier: Programming Language :: Python :: 3.6
Classifier: Programming Language :: Python :: 3.7
